{"ImagePath":"out/1593036800/1593036800_aljazeera.png","TimeStamp":1593036800,"Source":"aljazeera","original_result":"News\r\nDocumentaries\r\nShows\r\nOpinion\r\nMore\r\n3.\r\nO Live\r\nOPEN\r\nsea rchandnews.com\r\nWater Damage\r\nArab\r\nLeaguecall\r\nsraeVto drop\r\nannexation\r\nplans\r\nAt Security Council meeting, leaders warn\r\nIsrael's unilateral action in occupied West\r\nBank threatens peace prospects.\r\nProgressive Democrats\r\npush for changes to US\r\nIsrael policies\r\nTrump aide: Concerns\r\nover occupied West Bank\r\nannexation overblown\r\nEuropean MPs condemn\r\nIsrael's annexation move\r\nLIBYA\r\nLibya: Aguila Saleh\r\nurges Egypt to\r\nOPINION\r\nYoav Litvin\r\nBlack Lives Matter and\r\nlessons from Palestine\r\nSarah C Anderson-\r\nRajarigam & Sunita\r\nViswanath\r\nModi's India should be\r\non the US's religious\r\nfreedom blacklist\r\n","tokenized":["News","Documentaries","Shows","Opinion","More","3","O","Live","OPEN","sea","rchandnews","com","Water","Damage","Arab","Leaguecall","sraeVto","drop","annexation","plans","At","Security","Council","meeting","leaders","warn","Israel","s","unilateral","action","in","occupied","West","Bank","threatens","peace","prospects","Progressive","Democrats","push","for","changes","to","US","Israel","policies","Trump","aide","Concerns","over","occupied","West","Bank","annexation","overblown","European","MPs","condemn","Israel","s","annexation","move","LIBYA","Libya","Aguila","Saleh","urges","Egypt","to","OPINION","Yoav","Litvin","Black","Lives","Matter","and","lessons","from","Palestine","Sarah","C","Anderson","Rajarigam","Sunita","Viswanath","Modi","s","India","should","be","on","the","US","s","religious","freedom","blacklist"],"sentiment":{"score":-4,"comparative":-0.041237113402061855,"calculation":[{"freedom":2},{"matter":1},{"condemn":-2},{"prospects":1},{"peace":2},{"threatens":-2},{"warn":-2},{"drop":-1},{"damage":-3}],"tokens":["news","documentaries","shows","opinion","more","3","o","live","open","sea","rchandnews","com","water","damage","arab","leaguecall","sraevto","drop","annexation","plans","at","security","council","meeting","leaders","warn","israel","s","unilateral","action","in","occupied","west","bank","threatens","peace","prospects","progressive","democrats","push","for","changes","to","us","israel","policies","trump","aide","concerns","over","occupied","west","bank","annexation","overblown","european","mps","condemn","israel","s","annexation","move","libya","libya","aguila","saleh","urges","egypt","to","opinion","yoav","litvin","black","lives","matter","and","lessons","from","palestine","sarah","c","anderson","rajarigam","sunita","viswanath","modi","s","india","should","be","on","the","us","s","religious","freedom","blacklist"],"words":["freedom","matter","condemn","prospects","peace","threatens","warn","drop","damage"],"positive":["freedom","matter","prospects","peace"],"negative":["condemn","threatens","warn","drop","damage"]}}